lakecli/__init__.py
lakecli/clibuffer.py
lakecli/clistyle.py
lakecli/clitoolbar.py
lakecli/compat.py
lakecli/completer.py
lakecli/completion_refresher.py
lakecli/config.py
lakecli/encodingutils.py
lakecli/filters.py
lakecli/key_bindings.py
lakecli/lakeclirc
lakecli/lexer.py
lakecli/main.py
lakecli/sqlexecute.py
lakecli/style.py
lakecli/iam/__init__.py
lakecli/iam/orm.py
lakecli/iam/scanner.py
lakecli/packages/__init__.py
lakecli/packages/completion_engine.py
lakecli/packages/filepaths.py
lakecli/packages/parseutils.py
lakecli/packages/prompt_utils.py
lakecli/packages/literals/__init__.py
lakecli/packages/literals/literals.json
lakecli/packages/literals/main.py
lakecli/packages/special/__init__.py
lakecli/packages/special/dbcommands.py
lakecli/packages/special/favoritequeries.py
lakecli/packages/special/iocommands.py
lakecli/packages/special/main.py
lakecli/packages/special/utils.py
lakecli/packages/tabular_output/__init__.py
lakecli/packages/tabular_output/sql_format.py
lakecli/privileges/__init__.py
lakecli/privileges/grant_or_revoke.py
test/__init__.py
test/test_clistyle.py
test/test_completion_engine.py
test/test_completion_refresher.py
test/test_dbspecial.py
test/test_naive_completion.py
test/test_parseutils.py
test/test_privilege.py
test/test_prompt_utils.py
test/test_scanner.py
lakecli-0.2.0.dist-info/LICENSE
lakecli-0.2.0.dist-info/LICENSE.txt
lakecli-0.2.0.dist-info/METADATA
lakecli-0.2.0.dist-info/WHEEL
lakecli-0.2.0.dist-info/entry_points.txt
lakecli-0.2.0.dist-info/top_level.txt
lakecli-0.2.0.dist-info/RECORD
