Metadata-Version: 2.1
Name: lakecli
Version: 0.2.0
Summary: CLI for Athena Database and AWS Lake Formation. With auto-completion and syntax highlighting.
Home-page: https://github.com/tokern/lakecli
Author: dblintio
Author-email: lakecli@tokern.io
License: UNKNOWN
Platform: UNKNOWN
Classifier: Intended Audience :: Developers
Classifier: License :: OSI Approved :: BSD License
Classifier: Operating System :: Unix
Classifier: Programming Language :: Python
Classifier: Programming Language :: Python :: 3
Classifier: Programming Language :: Python :: 3.4
Classifier: Programming Language :: Python :: 3.5
Classifier: Programming Language :: Python :: 3.6
Classifier: Programming Language :: Python :: 3.7
Classifier: Programming Language :: SQL
Classifier: Topic :: Database
Classifier: Topic :: Database :: Front-Ends
Classifier: Topic :: Software Development
Classifier: Topic :: Software Development :: Libraries :: Python Modules
Requires-Dist: Pygments (>=1.6)
Requires-Dist: boto3 (>=1.4.4)
Requires-Dist: botocore (>=1.5.52)
Requires-Dist: cli-helpers[styles] (>=1.0.1)
Requires-Dist: click (>=4.1)
Requires-Dist: configobj (>=5.0.5)
Requires-Dist: peewee (>=3.11.2)
Requires-Dist: prompt-toolkit (<1.1.0,>=1.0.10)
Requires-Dist: sqlparse (<0.3.0,>=0.2.2)
